xero_db_connector/__init__.py
xero_db_connector/extract.py
xero_db_connector/extract_ddl.sql
xero_db_connector/load.py
xero_db_connector/load_ddl.sql
xero_db_connector-0.3.4.dist-info/LICENSE
xero_db_connector-0.3.4.dist-info/METADATA
xero_db_connector-0.3.4.dist-info/WHEEL
xero_db_connector-0.3.4.dist-info/top_level.txt
xero_db_connector-0.3.4.dist-info/RECORD
