Metadata-Version: 2.1
Name: xero-db-connector
Version: 0.3.4
Summary: Connects Xero to a database connector to transfer information to and fro.
Home-page: https://github.com/fylein/xero-db-connector
Author: Siva Narayanan
Author-email: siva@fyle.in
License: MIT
Keywords: xero,db,python,sdk,sqlite,postgres
Platform: UNKNOWN
Classifier: Topic :: Internet :: WWW/HTTP
Classifier: Intended Audience :: Developers
Classifier: Programming Language :: Python :: 3
Classifier: License :: OSI Approved :: MIT License
Classifier: Operating System :: OS Independent
Requires-Dist: pandas (==0.25.2)
Requires-Dist: pyxero (==0.9.1)
